sparkkgml/__init__.py
sparkkgml/data_acquisition.py
sparkkgml/data_augmentation.py
sparkkgml/feature_engineering.py
sparkkgml/feature_selection.py
sparkkgml/kg.py
sparkkgml/motif_walks.py
sparkkgml/semantification.py
sparkkgml/vectorization.py
sparkkgml-0.2.2.dist-info/LICENSE
sparkkgml-0.2.2.dist-info/METADATA
sparkkgml-0.2.2.dist-info/WHEEL
sparkkgml-0.2.2.dist-info/RECORD
