Metadata-Version: 2.1
Name: sparkkgml
Version: 0.2.2
Summary: From Knowledge Graphs to Machine Learning!
License: Apache-2.0
Author: IDIAS Lab
Requires-Python: >=3.8,<4.0
Classifier: License :: OSI Approved :: Apache Software License
Classifier: Programming Language :: Python :: 3
Classifier: Programming Language :: Python :: 3.8
Classifier: Programming Language :: Python :: 3.9
Classifier: Programming Language :: Python :: 3.10
Classifier: Programming Language :: Python :: 3.11
Requires-Dist: kgextension (>=0.1.1,<0.2.0)
Requires-Dist: pyspark (>=3.2,<4.0)
Requires-Dist: sparql-dataframe (>=0.4,<0.5)
